torch_tutor/__init__.py
torch_tutor/core/__init__.py
torch_tutor/core/callbacks.py
torch_tutor/core/trainer.py
torch_tutor/core/engine/__init__.py
torch_tutor/core/engine/loops.py
torch_tutor/metrics/__base__.py
torch_tutor/metrics/__init__.py
torch_tutor/metrics/generals.py
torch_tutor/utils/__init__.py
torch_tutor-0.0.4.dist-info/LICENSE
torch_tutor-0.0.4.dist-info/METADATA
torch_tutor-0.0.4.dist-info/WHEEL
torch_tutor-0.0.4.dist-info/top_level.txt
torch_tutor-0.0.4.dist-info/RECORD
