Metadata-Version: 2.1
Name: torch-tutor
Version: 0.0.4
Summary: Simplified PyTorch Trainer
Author: sagnik1511 (Sagnik Roy)
Author-email: <sagnik.jal00@gmail.com>
Keywords: python,pytorch,training,logging
Classifier: Development Status :: 1 - Planning
Classifier: Intended Audience :: Developers
Classifier: Programming Language :: Python :: 3
Classifier: Operating System :: Unix
Classifier: Operating System :: MacOS :: MacOS X
Classifier: Operating System :: Microsoft :: Windows
License-File: LICENSE
Requires-Dist: numpy
Requires-Dist: pandas
Requires-Dist: wandb
